doxcli/__init__.py
doxcli/bootstrap.py
doxcli/config/app.py
doxcli/exceptions/general.py
doxcli/services/faker/fakes.py
doxcli/services/godaddy/godaddy.py
doxcli/utils/file.py
doxcli/utils/general.py
doxcli-2.2.1.data/scripts/cli.py
doxcli-2.2.1.dist-info/LICENSE
doxcli-2.2.1.dist-info/METADATA
doxcli-2.2.1.dist-info/WHEEL
doxcli-2.2.1.dist-info/entry_points.txt
doxcli-2.2.1.dist-info/top_level.txt
doxcli-2.2.1.dist-info/RECORD
